Scopul/ChordProgression.py
Scopul/MusicalElements.py
Scopul/Sequence.py
Scopul/Tempo.py
Scopul/TimeSignature.py
Scopul/__init__.py
Scopul/config_musescore.py
Scopul/conversions.py
Scopul/helpers.py
Scopul/scopul.py
Scopul/scopul_exception.py
Scopul-1.1.4.dist-info/LICENSE
Scopul-1.1.4.dist-info/METADATA
Scopul-1.1.4.dist-info/WHEEL
Scopul-1.1.4.dist-info/top_level.txt
Scopul-1.1.4.dist-info/RECORD
